[
  {
    "id": "1",
    "name": "2024 Challenger SXT",
    "price": "30000",
    "image": "/temp/car1.png",
    "mileage": "21/28 City/Hwy",
    "engine": "4 cyl M",
    "driven": "1230 miles",
    "properties": ["No Accidents", "1  Owner", "Personal Use Only"],
    "seller": "VisiblePaths Auto Sales (15 mi away)"
  },
  {
    "id": "2",
    "name": "2024 Challenger SXT",
    "price": "30000",
    "image": "/temp/car2.png",
    "mileage": "21/28 City/Hwy",
    "engine": "4 cyl M",
    "driven": "1230 miles",
    "properties": ["No Accidents", "1  Owner", "Personal Use Only"],
    "seller": "VisiblePaths Auto Sales (15 mi away)"
  },
  {
    "id": "3",
    "name": "2024 Challenger SXT",
    "price": "30000",
    "image": "/temp/car3.png",
    "mileage": "21/28 City/Hwy",
    "engine": "4 cyl M",
    "driven": "1230 miles",
    "properties": ["No Accidents", "1  Owner", "Personal Use Only"],
    "seller": "VisiblePaths Auto Sales (15 mi away)"
  },
  {
    "id": "4",
    "name": "2024 Challenger SXT",
    "price": "30000",
    "image": "/temp/car1.png",
    "mileage": "21/28 City/Hwy",
    "engine": "4 cyl M",
    "driven": "1230 miles",
    "properties": ["No Accidents", "1  Owner", "Personal Use Only"],
    "seller": "VisiblePaths Auto Sales (15 mi away)"
  },
  {
    "id": "5",
    "name": "2024 Challenger SXT",
    "price": "30000",
    "image": "/temp/car4.png",
    "mileage": "21/28 City/Hwy",
    "engine": "4 cyl M",
    "driven": "1230 miles",
    "properties": ["No Accidents", "1  Owner", "Personal Use Only"],
    "seller": "VisiblePaths Auto Sales (15 mi away)"
  },
  {
    "id": "6",
    "name": "2024 Challenger SXT",
    "price": "30000",
    "image": "/temp/car2.png",
    "mileage": "21/28 City/Hwy",
    "engine": "4 cyl M",
    "driven": "1230 miles",
    "properties": ["No Accidents", "1  Owner", "Personal Use Only"],
    "seller": "VisiblePaths Auto Sales (15 mi away)"
  },
  {
    "id": "7",
    "name": "2024 Challenger SXT",
    "price": "30000",
    "image": "/temp/car3.png",
    "mileage": "21/28 City/Hwy",
    "engine": "4 cyl M",
    "driven": "1230 miles",
    "properties": ["No Accidents", "1  Owner", "Personal Use Only"],
    "seller": "VisiblePaths Auto Sales (15 mi away)"
  },
  {
    "id": "8",
    "name": "2024 Challenger SXT",
    "price": "30000",
    "image": "/temp/car4.png",
    "mileage": "21/28 City/Hwy",
    "engine": "4 cyl M",
    "driven": "1230 miles",
    "properties": ["No Accidents", "1  Owner", "Personal Use Only"],
    "seller": "VisiblePaths Auto Sales (15 mi away)"
  },
  {
    "id": "9",
    "name": "2024 Challenger SXT",
    "price": "30000",
    "image": "/temp/car1.png",
    "mileage": "21/28 City/Hwy",
    "engine": "4 cyl M",
    "driven": "1230 miles",
    "properties": ["No Accidents", "1  Owner", "Personal Use Only"],
    "seller": "VisiblePaths Auto Sales (15 mi away)"
  },
  {
    "id": "10",
    "name": "2024 Challenger SXT",
    "price": "30000",
    "image": "/temp/car3.png",
    "mileage": "21/28 City/Hwy",
    "engine": "4 cyl M",
    "driven": "1230 miles",
    "properties": ["No Accidents", "1  Owner", "Personal Use Only"],
    "seller": "VisiblePaths Auto Sales (15 mi away)"
  },
  {
    "id": "11",
    "name": "2024 Challenger SXT",
    "price": "30000",
    "image": "/temp/car2.png",
    "mileage": "21/28 City/Hwy",
    "engine": "4 cyl M",
    "driven": "1230 miles",
    "properties": ["No Accidents", "1  Owner", "Personal Use Only"],
    "seller": "VisiblePaths Auto Sales (15 mi away)"
  },
  {
    "id": "12",
    "name": "2024 Challenger SXT",
    "price": "30000",
    "image": "/temp/car4.png",
    "mileage": "21/28 City/Hwy",
    "engine": "4 cyl M",
    "driven": "1230 miles",
    "properties": ["No Accidents", "1  Owner", "Personal Use Only"],
    "seller": "VisiblePaths Auto Sales (15 mi away)"
  }
]
